{
  "basics": {
    "name": "Lionel Zovi",
    "label": "Full-stack Developer",
    "image": "assets/images/avatar.webp",
    "email": "lionel.zovi@gmail.com",
    "phone": "",
    "url": "https://escanor1986.github.io",
    "summary": "Full-stack developer with extensive experience in software development dating back to 2002, when I began programming with C++, Visual Basic, HTML, and hexadecimal code editing. With over 4 years of professional expertise in JavaScript/TypeScript, React, Node.js, and a solid grasp of Java-Angular stacks from ongoing professional training, I specialize in building scalable, secure, and performant applications. My background as a field and administrative police officer has endowed me with rigorous analytical skills, stress management, strong teamwork, and meticulous attention to detail. Passionate about technology and committed to continuous improvement, I bring structured problem-solving, reliability, and innovation to every project, ensuring high-quality outcomes tailored to complex professional environments.",
    "location": {},
    "profiles": [
      {
        "network": "GitHub",
        "username": "Escanor1986",
        "url": "https://github.com/Escanor1986"
      },
      {
        "network": "LinkedIn",
        "username": "lionelzovi",
        "url": "https://linkedin.com/in/lionelzovi"
      }
    ]
  },
  "work": [
    {
      "name": "Police Department",
      "position": "Police Officer",
      "startDate": "2007-03-01",
      "endDate": "",
      "summary": "Maintain public safety and enforce laws while fostering positive community relationships. Conduct investigations and write detailed reports on incidents. Train and mentor junior officers in operational procedures and best practices."
    },
    {
      "name": "NX Academy",
      "position": "Software Developer & Open-source Contributor",
      "startDate": "2023-03-01",
      "endDate": "",
      "summary": "Contributed to the development of the NX Academy learning platform using Astro.js. Developed and maintained components, ensuring scalability and performance. Improved platform features, optimized user experience, and authored technical documentation in JavaScript."
    },
    {
      "name": "OpenClassrooms & Personal Projects",
      "position": "Full-stack Developer",
      "startDate": "2021-03-01",
      "endDate": "",
      "summary": "Developed full-stack applications using JavaScript, TypeScript, Node.js, React, and MongoDB. Implemented frontend and backend features including APIs, authentication systems, and user management. Designed responsive user interfaces with Tailwind CSS and Bootstrap. Collaborated via GitHub and implemented CI/CD pipelines."
    }
  ],
  "education": [
    {
      "institution": "OpenClassrooms",
      "area": "Full-stack development (Java & Angular)",
      "studyType": "Expert Program",
      "startDate": "2024-01-01",
      "endDate": "2025-12-31"
    },
    {
      "institution": "NX Academy",
      "area": "Full-stack development (React & Node.js)",
      "studyType": "Online Program",
      "startDate": "2023-03-01",
      "endDate": "2024-06-01"
    },
    {
      "institution": "OpenClassrooms",
      "area": "Web Development (JavaScript)",
      "studyType": "Online Program",
      "startDate": "2022-03-01",
      "endDate": "2023-06-01"
    },
    {
      "institution": "Gembloux Agro-Bio Tech, ULG",
      "area": "Bio-Engineering (1st year)",
      "studyType": "Bachelor (1st year)",
      "startDate": "2018-09-01",
      "endDate": "2019-06-30"
    },
    {
      "institution": "Sart Tilman, ULG",
      "area": "Psychology (1st year)",
      "studyType": "Bachelor (1st year)",
      "startDate": "2011-09-01",
      "endDate": "2012-06-30"
    },
    {
      "institution": "University of Liège (ULG)",
      "area": "Criminology & Police",
      "studyType": "Training",
      "startDate": "2007-01-01",
      "endDate": "2009-12-31"
    },
    {
      "institution": "University of Liège (ULG)",
      "area": "Criminology & Police",
      "studyType": "Certification",
      "startDate": "2014-01-01",
      "endDate": "2014-12-31"
    },
    {
      "institution": "University of Liège (Liège)",
      "area": "Computer Science",
      "studyType": "Bachelor",
      "startDate": "1998-09-01",
      "endDate": "2004-06-30"
    }
  ],
  "skills": [
    {
      "name": "Frontend",
      "keywords": ["React", "NextJS", "Astro", "Angular", "Tailwind CSS", "HTML", "CSS", "SASS"]
    },
    {
      "name": "Backend",
      "keywords": ["Java", "Spring Boot", "Node.js", "Express.js", "Django"]
    },
    {
      "name": "Databases",
      "keywords": ["MySQL", "MongoDB", "Prisma", "PostgreSQL"]
    },
    {
      "name": "DevOps & Infrastructure",
      "keywords": ["Google Cloud", "Kubernetes", "GitHub Actions", "Docker", "Heroku", "Vercel", "OVH", "Mailgun"]
    },
    {
      "name": "Testing & Quality",
      "keywords": ["Mockito", "Jest", "Storybook", "Vitest"]
    },
    {
      "name": "Bundlers & Build Tools",
      "keywords": ["Webpack", "Vite"]
    }
  ],
  "languages": [
    {
      "language": "French",
      "fluency": "Native speaker"
    },
    {
      "language": "English",
      "fluency": "Professional"
    },
    {
      "language": "Dutch",
      "fluency": "Intermediate"
    },
    {
      "language": "Italian",
      "fluency": "Intermediate"
    }
  ]
}
